ariadne_relay/__init__.py
ariadne_relay/base.py
ariadne_relay/interfaces.py
ariadne_relay/node.py
ariadne_relay/objects.py
ariadne_relay/py.typed
ariadne_relay/utils.py
ariadne_relay/connection/__init__.py
ariadne_relay/connection/base.py
ariadne_relay/connection/proxy.py
ariadne_relay/connection/reference.py
ariadne_relay/connection/snake_case.py
ariadne_relay-0.1.0a8.dist-info/LICENSE
ariadne_relay-0.1.0a8.dist-info/METADATA
ariadne_relay-0.1.0a8.dist-info/WHEEL
ariadne_relay-0.1.0a8.dist-info/top_level.txt
ariadne_relay-0.1.0a8.dist-info/RECORD
