Metadata-Version: 2.1
Name: ariadne-relay
Version: 0.1.0a8
Summary: Ariadne-Relay provides a toolset for implementing GraphQL servers in Python that conform to the Relay specification, using the Ariadne library.
Home-page: https://github.com/g18e/ariadne-relay
Author: General Intelligence Inc.
Author-email: info@g18e.com
License: BSD
Platform: any
Classifier: Development Status :: 4 - Beta
Classifier: Intended Audience :: Developers
Classifier: License :: OSI Approved :: BSD License
Classifier: Operating System :: OS Independent
Classifier: Programming Language :: Python
Classifier: Programming Language :: Python :: 3.7
Classifier: Programming Language :: Python :: 3.8
Classifier: Programming Language :: Python :: 3.9
Classifier: Programming Language :: Python :: 3.10
Classifier: Topic :: Software Development :: Libraries :: Python Modules
License-File: LICENSE
Requires-Dist: ariadne (>=0.15.0)
Requires-Dist: graphql-relay (>=3.2.0)
